[{"crowdControlScore":0.0,"creepScorePM":4.7,"visionScorePM":0.1,"damagePM":351.2,"selfMitigatedPM":228.2,"KDA":8.0,"KP":0.53,"objectivesTaken":{"towerKills":0,"inhibitorKills":0,"riftHeraldKills":0,"dragonKills":0}},{"crowdControlScore":0.4,"creepScorePM":5.5,"visionScorePM":0.3,"damagePM":271.7,"selfMitigatedPM":408.2,"KDA":1.0,"KP":0.29,"objectivesTaken":{"towerKills":0,"inhibitorKills":0,"riftHeraldKills":0,"dragonKills":0}},{"crowdControlScore":0.2,"creepScorePM":6.9,"visionScorePM":0.2,"damagePM":460.9,"selfMitigatedPM":215.8,"KDA":4.0,"KP":0.52,"objectivesTaken":{"towerKills":0,"inhibitorKills":0,"riftHeraldKills":0,"dragonKills":1}},{"crowdControlScore":0.4,"creepScorePM":5.1,"visionScorePM":0.2,"damagePM":181.3,"selfMitigatedPM":198.8,"KDA":0.4,"KP":0.29,"objectivesTaken":{"towerKills":0,"inhibitorKills":0,"riftHeraldKills":0,"dragonKills":0}},{"crowdControlScore":0.0,"creepScorePM":6.4,"visionScorePM":0.1,"damagePM":255.4,"selfMitigatedPM":264.4,"KDA":0.8,"KP":0.31,"objectivesTaken":{"towerKills":0,"inhibitorKills":0,"riftHeraldKills":0,"dragonKills":2}},{"crowdControlScore":0.4,"creepScorePM":7.2,"visionScorePM":0.6,"damagePM":1039.6,"selfMitigatedPM":484.9,"KDA":6.2,"KP":0.72,"objectivesTaken":{"towerKills":0,"inhibitorKills":0,"riftHeraldKills":0,"dragonKills":1}},{"crowdControlScore":0.0,"creepScorePM":6.4,"visionScorePM":0.5,"damagePM":679.5,"selfMitigatedPM":217.4,"KDA":2.3,"KP":0.57,"objectivesTaken":{"towerKills":0,"inhibitorKills":0,"riftHeraldKills":0,"dragonKills":1}},{"crowdControlScore":0.6,"creepScorePM":4.8,"visionScorePM":0.1,"damagePM":474.2,"selfMitigatedPM":281.0,"KDA":1.6,"KP":0.46,"objectivesTaken":{"towerKills":0,"inhibitorKills":0,"riftHeraldKills":0,"dragonKills":0}},{"crowdControlScore":0.1,"creepScorePM":4.2,"visionScorePM":0.5,"damagePM":589.2,"selfMitigatedPM":351.7,"KDA":1.7,"KP":0.31,"objectivesTaken":{"towerKills":0,"inhibitorKills":0,"riftHeraldKills":0,"dragonKills":2}},{"crowdControlScore":0.4,"creepScorePM":4.8,"visionScorePM":0.2,"damagePM":597.2,"selfMitigatedPM":576.7,"KDA":1.1,"KP":0.32,"objectivesTaken":{"towerKills":0,"inhibitorKills":0,"riftHeraldKills":0,"dragonKills":0}},{"crowdControlScore":0.3,"creepScorePM":5.6,"visionScorePM":0.2,"damagePM":189.0,"selfMitigatedPM":86.3,"KDA":9.2233720368547763E17,"KP":0.39,"objectivesTaken":{"towerKills":0,"inhibitorKills":0,"riftHeraldKills":0,"dragonKills":1}},{"crowdControlScore":0.1,"creepScorePM":5.5,"visionScorePM":0.2,"damagePM":410.9,"selfMitigatedPM":185.7,"KDA":0.9,"KP":0.43,"objectivesTaken":{"towerKills":0,"inhibitorKills":0,"riftHeraldKills":0,"dragonKills":0}},{"crowdControlScore":0.0,"creepScorePM":4.1,"visionScorePM":0.5,"damagePM":687.6,"selfMitigatedPM":343.6,"KDA":3.1,"KP":0.51,"objectivesTaken":{"towerKills":0,"inhibitorKills":0,"riftHeraldKills":0,"dragonKills":1}},{"crowdControlScore":0.3,"creepScorePM":6.6,"visionScorePM":0.3,"damagePM":530.1,"selfMitigatedPM":542.1,"KDA":2.3,"KP":0.35,"objectivesTaken":{"towerKills":0,"inhibitorKills":0,"riftHeraldKills":0,"dragonKills":0}},{"crowdControlScore":0.8,"creepScorePM":5.2,"visionScorePM":0.9,"damagePM":685.5,"selfMitigatedPM":298.0,"KDA":2.4,"KP":0.57,"objectivesTaken":{"towerKills":0,"inhibitorKills":0,"riftHeraldKills":0,"dragonKills":0}},{"crowdControlScore":0.3,"creepScorePM":3.4,"visionScorePM":0.6,"damagePM":598.5,"selfMitigatedPM":323.9,"KDA":2.1,"KP":0.48,"objectivesTaken":{"towerKills":0,"inhibitorKills":0,"riftHeraldKills":0,"dragonKills":1}},{"crowdControlScore":0.8,"creepScorePM":4.2,"visionScorePM":0.1,"damagePM":446.1,"selfMitigatedPM":159.9,"KDA":6.5,"KP":0.48,"objectivesTaken":{"towerKills":0,"inhibitorKills":0,"riftHeraldKills":0,"dragonKills":2}},{"crowdControlScore":0.4,"creepScorePM":6.0,"visionScorePM":0.7,"damagePM":631.1,"selfMitigatedPM":272.9,"KDA":4.4,"KP":0.56,"objectivesTaken":{"towerKills":0,"inhibitorKills":0,"riftHeraldKills":0,"dragonKills":0}},{"crowdControlScore":0.8,"creepScorePM":6.2,"visionScorePM":0.4,"damagePM":639.2,"selfMitigatedPM":290.4,"KDA":10.5,"KP":0.5,"objectivesTaken":{"towerKills":0,"inhibitorKills":0,"riftHeraldKills":0,"dragonKills":2}},{"crowdControlScore":0.3,"creepScorePM":6.1,"visionScorePM":0.3,"damagePM":298.6,"selfMitigatedPM":167.8,"KDA":11.0,"KP":0.33,"objectivesTaken":{"towerKills":0,"inhibitorKills":0,"riftHeraldKills":0,"dragonKills":0}},{"crowdControlScore":0.3,"creepScorePM":5.4,"visionScorePM":0.4,"damagePM":734.5,"selfMitigatedPM":550.1,"KDA":2.1,"KP":0.46,"objectivesTaken":{"towerKills":0,"inhibitorKills":0,"riftHeraldKills":0,"dragonKills":1}},{"crowdControlScore":0.6,"creepScorePM":4.8,"visionScorePM":0.0,"damagePM":547.4,"selfMitigatedPM":322.6,"KDA":0.3,"KP":0.27,"objectivesTaken":{"towerKills":0,"inhibitorKills":0,"riftHeraldKills":0,"dragonKills":0}},{"crowdControlScore":1.0,"creepScorePM":3.9,"visionScorePM":0.4,"damagePM":618.3,"selfMitigatedPM":364.7,"KDA":2.3,"KP":0.57,"objectivesTaken":{"towerKills":0,"inhibitorKills":0,"riftHeraldKills":0,"dragonKills":0}},{"crowdControlScore":0.6,"creepScorePM":5.4,"visionScorePM":1.2,"damagePM":1490.8,"selfMitigatedPM":516.7,"KDA":6.6,"KP":0.66,"objectivesTaken":{"towerKills":0,"inhibitorKills":0,"riftHeraldKills":0,"dragonKills":1}},{"crowdControlScore":0.4,"creepScorePM":5.6,"visionScorePM":0.2,"damagePM":291.3,"selfMitigatedPM":308.6,"KDA":1.5,"KP":0.67,"objectivesTaken":{"towerKills":0,"inhibitorKills":0,"riftHeraldKills":0,"dragonKills":0}},{"crowdControlScore":0.0,"creepScorePM":5.5,"visionScorePM":0.5,"damagePM":443.9,"selfMitigatedPM":264.0,"KDA":2.3,"KP":0.33,"objectivesTaken":{"towerKills":0,"inhibitorKills":0,"riftHeraldKills":0,"dragonKills":1}},{"crowdControlScore":0.0,"creepScorePM":4.2,"visionScorePM":0.4,"damagePM":482.0,"selfMitigatedPM":222.1,"KDA":3.3,"KP":0.37,"objectivesTaken":{"towerKills":0,"inhibitorKills":0,"riftHeraldKills":0,"dragonKills":1}},{"crowdControlScore":0.5,"creepScorePM":4.9,"visionScorePM":0.5,"damagePM":1100.2,"selfMitigatedPM":633.5,"KDA":3.8,"KP":0.58,"objectivesTaken":{"towerKills":0,"inhibitorKills":0,"riftHeraldKills":0,"dragonKills":1}},{"crowdControlScore":0.4,"creepScorePM":5.2,"visionScorePM":0.6,"damagePM":974.8,"selfMitigatedPM":685.4,"KDA":3.4,"KP":0.57,"objectivesTaken":{"towerKills":0,"inhibitorKills":0,"riftHeraldKills":0,"dragonKills":2}},{"crowdControlScore":0.4,"creepScorePM":5.0,"visionScorePM":0.4,"damagePM":1032.9,"selfMitigatedPM":560.9,"KDA":2.3,"KP":0.44,"objectivesTaken":{"towerKills":0,"inhibitorKills":0,"riftHeraldKills":0,"dragonKills":1}},{"crowdControlScore":0.0,"creepScorePM":4.2,"visionScorePM":0.3,"damagePM":378.2,"selfMitigatedPM":397.8,"KDA":1.5,"KP":0.28,"objectivesTaken":{"towerKills":0,"inhibitorKills":0,"riftHeraldKills":0,"dragonKills":0}},{"crowdControlScore":0.1,"creepScorePM":6.5,"visionScorePM":0.5,"damagePM":825.9,"selfMitigatedPM":334.2,"KDA":6.5,"KP":0.46,"objectivesTaken":{"towerKills":0,"inhibitorKills":0,"riftHeraldKills":0,"dragonKills":1}},{"crowdControlScore":1.2,"creepScorePM":3.8,"visionScorePM":0.3,"damagePM":696.6,"selfMitigatedPM":241.8,"KDA":12.0,"KP":0.47,"objectivesTaken":{"towerKills":0,"inhibitorKills":0,"riftHeraldKills":0,"dragonKills":0}},{"crowdControlScore":0.4,"creepScorePM":4.9,"visionScorePM":0.2,"damagePM":514.3,"selfMitigatedPM":331.4,"KDA":1.4,"KP":0.5,"objectivesTaken":{"towerKills":0,"inhibitorKills":0,"riftHeraldKills":0,"dragonKills":1}},{"crowdControlScore":0.0,"creepScorePM":5.6,"visionScorePM":0.3,"damagePM":546.5,"selfMitigatedPM":491.0,"KDA":1.8,"KP":0.3,"objectivesTaken":{"towerKills":0,"inhibitorKills":0,"riftHeraldKills":0,"dragonKills":1}},{"crowdControlScore":0.5,"creepScorePM":6.5,"visionScorePM":0.2,"damagePM":511.7,"selfMitigatedPM":216.8,"KDA":5.3,"KP":0.48,"objectivesTaken":{"towerKills":0,"inhibitorKills":0,"riftHeraldKills":0,"dragonKills":1}},{"crowdControlScore":0.7,"creepScorePM":5.5,"visionScorePM":0.2,"damagePM":902.8,"selfMitigatedPM":392.3,"KDA":6.5,"KP":0.5,"objectivesTaken":{"towerKills":0,"inhibitorKills":0,"riftHeraldKills":0,"dragonKills":1}},{"crowdControlScore":0.6,"creepScorePM":6.7,"visionScorePM":0.7,"damagePM":524.9,"selfMitigatedPM":145.8,"KDA":2.8,"KP":0.33,"objectivesTaken":{"towerKills":0,"inhibitorKills":0,"riftHeraldKills":0,"dragonKills":0}},{"crowdControlScore":0.7,"creepScorePM":6.2,"visionScorePM":0.1,"damagePM":637.2,"selfMitigatedPM":174.5,"KDA":3.8,"KP":0.42,"objectivesTaken":{"towerKills":0,"inhibitorKills":0,"riftHeraldKills":0,"dragonKills":0}},{"crowdControlScore":0.0,"creepScorePM":6.7,"visionScorePM":0.7,"damagePM":810.9,"selfMitigatedPM":162.1,"KDA":9.5,"KP":0.58,"objectivesTaken":{"towerKills":0,"inhibitorKills":0,"riftHeraldKills":0,"dragonKills":0}},{"crowdControlScore":0.9,"creepScorePM":5.8,"visionScorePM":0.2,"damagePM":990.6,"selfMitigatedPM":283.2,"KDA":14.0,"KP":0.78,"objectivesTaken":{"towerKills":0,"inhibitorKills":0,"riftHeraldKills":0,"dragonKills":0}},{"crowdControlScore":0.1,"creepScorePM":6.1,"visionScorePM":0.5,"damagePM":912.0,"selfMitigatedPM":290.7,"KDA":5.0,"KP":0.63,"objectivesTaken":{"towerKills":0,"inhibitorKills":0,"riftHeraldKills":0,"dragonKills":0}},{"crowdControlScore":0.7,"creepScorePM":5.6,"visionScorePM":0.5,"damagePM":456.6,"selfMitigatedPM":311.3,"KDA":2.0,"KP":0.64,"objectivesTaken":{"towerKills":0,"inhibitorKills":0,"riftHeraldKills":0,"dragonKills":0}},{"crowdControlScore":0.7,"creepScorePM":6.2,"visionScorePM":1.0,"damagePM":810.2,"selfMitigatedPM":309.6,"KDA":2.8,"KP":0.59,"objectivesTaken":{"towerKills":0,"inhibitorKills":0,"riftHeraldKills":0,"dragonKills":2}},{"crowdControlScore":0.5,"creepScorePM":5.1,"visionScorePM":0.3,"damagePM":621.6,"selfMitigatedPM":187.0,"KDA":11.5,"KP":0.55,"objectivesTaken":{"towerKills":0,"inhibitorKills":0,"riftHeraldKills":0,"dragonKills":0}}]